AIML_Sets-1.0.1.dist-info/DESCRIPTION.rst
AIML_Sets-1.0.1.dist-info/METADATA
AIML_Sets-1.0.1.dist-info/RECORD
AIML_Sets-1.0.1.dist-info/WHEEL
AIML_Sets-1.0.1.dist-info/metadata.json
AIML_Sets-1.0.1.dist-info/top_level.txt
aiml_sets/__init__.py
aiml_sets/alice/ai.aiml
aiml_sets/alice/alice.aiml
aiml_sets/alice/astrology.aiml
aiml_sets/alice/atomic.aiml
aiml_sets/alice/badanswer.aiml
aiml_sets/alice/biography.aiml
aiml_sets/alice/bot.aiml
aiml_sets/alice/bot_profile.aiml
aiml_sets/alice/client.aiml
aiml_sets/alice/client_profile.aiml
aiml_sets/alice/computers.aiml
aiml_sets/alice/continuation.aiml
aiml_sets/alice/date.aiml
aiml_sets/alice/default.aiml
aiml_sets/alice/drugs.aiml
aiml_sets/alice/emotion.aiml
aiml_sets/alice/food.aiml
aiml_sets/alice/geography.aiml
aiml_sets/alice/gossip.aiml
aiml_sets/alice/history.aiml
aiml_sets/alice/humor.aiml
aiml_sets/alice/imponderables.aiml
aiml_sets/alice/inquiry.aiml
aiml_sets/alice/interjection.aiml
aiml_sets/alice/iu.aiml
aiml_sets/alice/knowledge.aiml
aiml_sets/alice/literature.aiml
aiml_sets/alice/loebner10.aiml
aiml_sets/alice/money.aiml
aiml_sets/alice/movies.aiml
aiml_sets/alice/mp0.aiml
aiml_sets/alice/mp1.aiml
aiml_sets/alice/mp2.aiml
aiml_sets/alice/mp3.aiml
aiml_sets/alice/mp4.aiml
aiml_sets/alice/mp5.aiml
aiml_sets/alice/mp6.aiml
aiml_sets/alice/music.aiml
aiml_sets/alice/numbers.aiml
aiml_sets/alice/personality.aiml
aiml_sets/alice/phone.aiml
aiml_sets/alice/pickup.aiml
aiml_sets/alice/politics.aiml
aiml_sets/alice/primeminister.aiml
aiml_sets/alice/psychology.aiml
aiml_sets/alice/pyschology.aiml
aiml_sets/alice/reduction0.safe.aiml
aiml_sets/alice/reduction1.safe.aiml
aiml_sets/alice/reduction2.safe.aiml
aiml_sets/alice/reduction3.safe.aiml
aiml_sets/alice/reduction4.safe.aiml
aiml_sets/alice/reductions-update.aiml
aiml_sets/alice/religion.aiml
aiml_sets/alice/salutations.aiml
aiml_sets/alice/science.aiml
aiml_sets/alice/sex.aiml
aiml_sets/alice/sports.aiml
aiml_sets/alice/stack.aiml
aiml_sets/alice/stories.aiml
aiml_sets/alice/that.aiml
aiml_sets/alice/update1.aiml
aiml_sets/alice/wallace.aiml
aiml_sets/alice/xfind.aiml
aiml_sets/mitsuku/20q.aiml
