Metadata-Version: 2.0
Name: AIML-Sets
Version: 1.0.1
Summary: AIML sets (ALICE & Mitsuku)
Home-page: https://github.com/hosford42/AIML_Sets
Author: Aaron Hosford
Author-email: hosford42@gmail.com
License: GNU GPL
Platform: UNKNOWN
